utis/AntsFight.py
utis/Fractions.py
utis/__init__.py
utis/complex.py
utis/html.py
utis/nodes.py
utis/noeyuds.py
utis/plan.py
utis/vec.py
utis_matisse-0.6.9420.dist-info/LICENCE
utis_matisse-0.6.9420.dist-info/METADATA
utis_matisse-0.6.9420.dist-info/WHEEL
utis_matisse-0.6.9420.dist-info/top_level.txt
utis_matisse-0.6.9420.dist-info/RECORD
