Metadata-Version: 2.1
Name: utis-matisse
Version: 0.6.9420
Summary: Potits trucs utils on ne sait jamais
Home-page: UNKNOWN
Author: momoladebrouill
Author-email: <momoladebrouill@github.io>
License: UNKNOWN
Keywords: python,maths,OOP
Platform: UNKNOWN
Classifier: Development Status :: 1 - Planning
Classifier: Intended Audience :: Developers
Classifier: Programming Language :: Python :: 3
Classifier: Operating System :: Unix
Classifier: Operating System :: MacOS :: MacOS X
Classifier: Operating System :: Microsoft :: Windows
